pynput/__init__.py
pynput/_info.py
pynput/_util/__init__.py
pynput/_util/darwin.py
pynput/_util/darwin_vks.py
pynput/_util/uinput.py
pynput/_util/win32.py
pynput/_util/win32_vks.py
pynput/_util/xorg.py
pynput/_util/xorg_keysyms.py
pynput/keyboard/__init__.py
pynput/keyboard/_base.py
pynput/keyboard/_darwin.py
pynput/keyboard/_dummy.py
pynput/keyboard/_uinput.py
pynput/keyboard/_win32.py
pynput/keyboard/_xorg.py
pynput/mouse/__init__.py
pynput/mouse/_base.py
pynput/mouse/_darwin.py
pynput/mouse/_dummy.py
pynput/mouse/_win32.py
pynput/mouse/_xorg.py
pynput-1.7.6.dist-info/COPYING.LGPL
pynput-1.7.6.dist-info/METADATA
pynput-1.7.6.dist-info/WHEEL
pynput-1.7.6.dist-info/pbr.json
pynput-1.7.6.dist-info/top_level.txt
pynput-1.7.6.dist-info/zip-safe
pynput-1.7.6.dist-info/RECORD
